deadpool.py
deadpool_executor-2025.2.2.dist-info/LICENSE-AGPL
deadpool_executor-2025.2.2.dist-info/LICENSE-Apache
deadpool_executor-2025.2.2.dist-info/WHEEL
deadpool_executor-2025.2.2.dist-info/METADATA
deadpool_executor-2025.2.2.dist-info/RECORD
