Metadata-Version: 2.3
Name: deadpool-executor
Version: 2025.2.2
Summary: Deadpool
Author-email: Caleb Hattingh <caleb.hattingh@gmail.com>
Classifier: License :: OSI Approved :: GNU Affero General Public License v3 or later (AGPLv3+)
Classifier: License :: OSI Approved :: Apache Software License
Classifier: Development Status :: 3 - Alpha
Classifier: Intended Audience :: Developers
Classifier: Operating System :: POSIX :: Linux
Classifier: Programming Language :: Python :: 3.9
Classifier: Programming Language :: Python :: 3.10
Classifier: Programming Language :: Python :: 3.11
Classifier: Programming Language :: Python :: 3.12
Classifier: Programming Language :: Python :: 3.13
Classifier: Programming Language :: Python :: Implementation
Classifier: Programming Language :: Python :: Implementation :: CPython
Requires-Dist: psutil
Requires-Dist: pytest >= 7 ; extra == "test"
Requires-Dist: pytest-cov ; extra == "test"
Requires-Dist: flake8 ; extra == "test"
Requires-Dist: coverage[toml] ; extra == "test"
Project-URL: Documentation, https://github.com/cjrh/deadpool
Project-URL: Home, https://github.com/cjrh/deadpool
Project-URL: Source, https://github.com/cjrh/deadpool
Provides-Extra: test
